stringzillas.cp313-win_amd64.pyd
cli/__init__.py
cli/split.py
cli/wc.py
stringzillas_cpus-4.6.0.dist-info/licenses/LICENSE
stringzillas_cpus-4.6.0.dist-info/METADATA
stringzillas_cpus-4.6.0.dist-info/WHEEL
stringzillas_cpus-4.6.0.dist-info/top_level.txt
stringzillas_cpus-4.6.0.dist-info/RECORD
